cleaning/__init__.py
cleaning/ukdata_cleaning.py
graphs/__init__.py
htmlgen/__init__.py
maps/__init__.py
spiegel_lib-0.1.0.dist-info/licenses/LICENSE
spiegel_lib-0.1.0.dist-info/METADATA
spiegel_lib-0.1.0.dist-info/WHEEL
spiegel_lib-0.1.0.dist-info/top_level.txt
spiegel_lib-0.1.0.dist-info/RECORD
