Metadata-Version: 2.4
Name: spiegel-lib
Version: 0.1.0
Summary: Provides data analysis tool for government crime data.
Author-email: Igor Carvalheira <igorccarvalheira111@gmail.com>
License: MIT License
Requires-Python: >=3.8
License-File: LICENSE
Requires-Dist: requests>=2.25.1
Requires-Dist: polars>=1.31.0
Dynamic: license-file
